xview/__init__.py
xview/xview.py
xview-0.0.6.data/data/LICENSE
xview-0.0.6.dist-info/LICENSE
xview-0.0.6.dist-info/METADATA
xview-0.0.6.dist-info/WHEEL
xview-0.0.6.dist-info/top_level.txt
xview-0.0.6.dist-info/RECORD
