Metadata-Version: 2.1
Name: xview
Version: 0.0.6
Summary: Examine memory views/bytes pretty printing it.
Home-page: https://github.com/bad-address/xview
Author: Di Paola Martin
Author-email: use-github-issues@example.com
License: GNU LGPLv3
Platform: UNKNOWN
Classifier: Development Status :: 3 - Alpha
Classifier: Intended Audience :: Developers
Classifier: License :: OSI Approved :: GNU General Public License v3 (GPLv3)
Classifier: Programming Language :: Python :: 3.5
Classifier: Programming Language :: Python :: 3.6
Classifier: Programming Language :: Python :: 3.7
Classifier: Programming Language :: Python :: 3.8
Classifier: Programming Language :: Python :: 3.9
Requires-Python: >=3.5
Requires-Dist: more-itertools
